{"trial_id": "3", "hyperparameters": {"space": [{"class_name": "Choice", "config": {"name": "state_dim", "default": 20, "conditions": [], "values": [20], "ordered": true}}, {"class_name": "Choice", "config": {"name": "dropout", "default": 0.0, "conditions": [], "values": [0.0, 0.4, 0.5, 0.6], "ordered": true}}, {"class_name": "Choice", "config": {"name": "learning_rate", "default": 0.01, "conditions": [], "values": [0.01, 0.001, 0.0001], "ordered": true}}], "values": {"state_dim": 20, "dropout": 0.0, "learning_rate": 0.0001}}, "metrics": {"metrics": {"loss": {"direction": "min", "observations": [{"value": [0.34510600566864014], "step": 2}]}, "accuracy": {"direction": "max", "observations": [{"value": [0.8715000152587891], "step": 2}]}, "val_loss": {"direction": "min", "observations": [{"value": [0.4548024535179138], "step": 2}]}, "val_accuracy": {"direction": "max", "observations": [{"value": [0.8027999997138977], "step": 2}]}}}, "score": 0.8027999997138977, "best_step": 2, "status": "COMPLETED", "message": null}